torch_image_lerp/__init__.py
torch_image_lerp/grid_sample_utils.py
torch_image_lerp/linear_interpolation_2d.py
torch_image_lerp/linear_interpolation_3d.py
torch_image_lerp-0.0.5.dist-info/METADATA
torch_image_lerp-0.0.5.dist-info/WHEEL
torch_image_lerp-0.0.5.dist-info/licenses/LICENSE
torch_image_lerp-0.0.5.dist-info/RECORD
